SPINSpy-1.0.0.dist-info/DESCRIPTION.rst
SPINSpy-1.0.0.dist-info/METADATA
SPINSpy-1.0.0.dist-info/RECORD
SPINSpy-1.0.0.dist-info/WHEEL
SPINSpy-1.0.0.dist-info/metadata.json
SPINSpy-1.0.0.dist-info/top_level.txt
matpy/FiniteDiff.py
matpy/__init__.py
matpy/cheb.py
matpy/circular_map.py
matpy/darkjet.py
matpy/lightbalance.py
spinspy/__init__.py
spinspy/get_diagnostics.py
spinspy/get_grid.py
spinspy/get_gridparams.py
spinspy/get_params.py
spinspy/isdim.py
spinspy/nearestindex.py
spinspy/reader.py
spinspy/set_path.py
spinspy/spinspy_classes.py
