Metadata-Version: 2.0
Name: SPINSpy
Version: 1.0.0
Summary: A set of python tools for processing SPINS outputs.
Home-page: https://git.uwaterloo.ca/bastorer/SPINSpy
Author: Ben Storer
Author-email: bastorer@uwaterloo.ca
License: UNKNOWN
Project-URL: Documentation, https://git.uwaterloo.ca/bastorer/SPINSpy/wikis/home
Project-URL: Source, https://git.uwaterloo.ca/bastorer/SPINSpy
Platform: UNKNOWN
Classifier: Programming Language :: Python :: 3
Classifier: License :: OSI Approved :: MIT License
Classifier: Operating System :: OS Independent
